causallift/__init__.py
causallift/causal_lift.py
causallift/generate_data.py
causallift/pipeline.py
causallift/run.py
causallift/context/__init__.py
causallift/context/base_context.py
causallift/context/flexible_context.py
causallift/nodes/__init__.py
causallift/nodes/estimate_propensity.py
causallift/nodes/model_for_each.py
causallift/nodes/utils.py
causallift-1.0.6.dist-info/DESCRIPTION.rst
causallift-1.0.6.dist-info/METADATA
causallift-1.0.6.dist-info/RECORD
causallift-1.0.6.dist-info/WHEEL
causallift-1.0.6.dist-info/entry_points.txt
causallift-1.0.6.dist-info/metadata.json
causallift-1.0.6.dist-info/top_level.txt
